{
  "id": 16,
  "robots": [
    {"id": "wineeurope", "name": "WineEurope"},
    {"id": "lebrobot-james", "name": "LeBROBOT JAMES"}
  ],
  "startingBaskets": ["blue", "magenta"],
  "isTieAllowed": true,
  "hasEnded": false,
  "rounds": [
    {
      "scores": [[], []],
      "fouls": [[], []],
      "baskets": ["blue", "magenta"],
      "hasEnded": false,
      "isConfirmed": false,
      "roundMaxLength": 60000,
      "runs": []
    }
  ],
  "ballPlacement": [
    [0, 0],
    [-0.03, 1.33],
    [0.03, -1.33],
    [1.78, 0.28],
    [-1.78, -0.28],
    [1.1, -0.05],
    [-1.1, 0.05],
    [0.76, 0.48],
    [-0.76, -0.48],
    [-0.16, 0.19],
    [0.16, -0.19]
  ]
}